{
  "categorias": [
    {
      "titulo": "Games",
      "link": "https://linktr.ee/carolsvntos",
      "cor": "#f368e0",
      "link_extra": {
        "text": "Games que eu gosto ou quero jogar",
        "url": "https://twitter.com/carolsvntos"
      },
      "videos": [
        {
          "titulo": "Final Fantasy VII Remake - Theme Song Trailer | PS4",
          "url": "https://www.youtube.com/watch?v=YkXG08_WVsY"
        },
        {
          "titulo": "Ghost of Tsushima - Official Story Trailer",
          "url": "https://www.youtube.com/watch?v=b_iU_gnn28U"
        },
        {
          "titulo": "Overwatch Animated Short | “Shooting Star”",
          "url": "https://www.youtube.com/watch?v=q7j2d6YCQbg"
        },  
        {
          "titulo": "Persona 5 Royal - Official Trailer",
          "url": "https://www.youtube.com/watch?v=SKpSpvFCZRw"
        },
        {
          "titulo": "Animal Crossing: New Horizons - Nintendo Switch Trailer - Nintendo E3 2019          ",
          "url": "https://www.youtube.com/watch?v=_3YNL0OWio0"
        },
        {
          "titulo": "Cyberpunk 2077 — Official Trailer — The Gig",
          "url": "https://www.youtube.com/watch?v=ixl31324UxE"
        },
        {
          "titulo": "Death Stranding - Launch Trailer | PS4",
          "url": "https://www.youtube.com/watch?v=tCI396HyhbQ"
        },
        {
          "titulo": "The Last of Us Part 2 - Official Story Trailer",
          "url": "https://www.youtube.com/watch?v=X0VubwgS2Y4"
        }      
      ]
    },
    {
      "titulo": "Música",
      "cor": "#ff9f43",
      "link_extra": {
        "text": "Músicas que comecei a ouvir esse mês",
        "url": "https://twitter.com/carolsvntos"
      },
      "videos": [
        {
          "titulo": "God Only Knows (Remastered)",
          "url": "https://www.youtube.com/watch?v=CWPo5SC3zik"
        },
        {
          "titulo": "Your Own Special Way (Remaster 2007)",
          "url": "https://www.youtube.com/watch?v=oKIYxq6Sbd8"
        },
        {
          "titulo": "I'll Be Lucky Someday (Remastered 2001)",
          "url": "https://www.youtube.com/watch?v=clwyL21oTs0"
        }, 
        {
          "titulo": "Roundabout (2008 Remastered Version)",
          "url": "https://www.youtube.com/watch?v=cPCLFtxpadE"
        }
      ]
    },
    {
      "titulo": "Culinária",
      "cor": "#ee5253",
      "link_extra": {
        "text": "Receitas que pretendo experimentar",
        "url": "https://twitter.com/carolsvntos"
      },
      "videos": [
        {
          "titulo": "The Best Homemade Pasta You'll Ever Eat",
          "url": "https://www.youtube.com/watch?v=YNHqjFyk5gU"
        },
        {
          "titulo": "Healthier Versions of Unhealthy Foods | Basics with Babish",
          "url": "https://www.youtube.com/watch?v=yYUUobrsFDs"
        },
        {
          "titulo": "Estrogonofe de carne | Rita Lobo | Cozinha Prática",
          "url": "https://www.youtube.com/watch?v=gHfFdaeaGoY"
        },
        {
          "titulo": "KIMCHI | Receita Coreana",
          "url": "https://www.youtube.com/watch?v=msk8T3Q1FGI"
        }
      ]
    },
    {
      "titulo": "Jardinagem",
      "cor": "#10ac84",
      "link_extra": {
        "text": "Algumas dicas que estou seguindo com minhas plantinhas",
        "url": "https://twitter.com/carolsvntos"
      },
      "videos": [
        {
          "titulo": "MITOS E VERDADES na Jardinagem",
          "url": "https://www.youtube.com/watch?v=Xb4tKEiD6bk"
        },
        {
          "titulo": "7 ERROS na JARDINAGEM que todo mundo comete",
          "url": "https://www.youtube.com/watch?v=ssVZQzw9RKc"
        },
        {
          "titulo": "Dicas de plantas fáceis de cuidar | Jardinagem | Gabi Pileggi",
          "url": "https://www.youtube.com/watch?v=eoWGQBQDALE"
        },
        {
          "titulo": "SUCULENTAS: 3 DICAS que ninguém conta",
          "url": "https://www.youtube.com/watch?v=rErKYAdePns"
        },
        {
          "titulo": "Jardim vertical de baixo custo",
          "url": "https://www.youtube.com/watch?v=Aznxz1rtTlI"
        }
      ]
    },
    {
      "titulo": "Podcasts",
      "cor": "#0abde3",
      "link_extra": {
        "text": "Podcasts que ouço no próprio YouTube",
        "url": "https://twitter.com/carolsvntos"
      },
      "videos": [
        {
          "titulo": "O que é JavaScript? | #HipstersPontoTube",
          "url": "https://www.youtube.com/watch?v=NaVSbnnV75Q"
        },
        {
          "titulo": "SEU FRANCISCO",
          "url": "https://www.youtube.com/watch?v=uFRigtgjM-c"
        },
        {
          "titulo": "Getting Swept Up in Romantic Gestures - Ep 28 - Big Mood",
          "url": "https://www.youtube.com/watch?v=lFxaTwf22HU"
        },
        {
          "titulo": "Eric Andre - H3 Podcast #195",
          "url": "https://www.youtube.com/watch?v=H28q3GpraK8"
        },
        {
          "titulo": "Family Reunited with Kidnapped Son After 32 Years (ft. Tim Chantarangsu)",
          "url": "https://www.youtube.com/watch?v=Jlyf4GANHtk"
        }
      ]
    }
  ]
}